README.md
roseingrave/__init__.py
roseingrave/__main__.py
roseingrave/__version__.py
roseingrave/_input_files.py
roseingrave/_output_files.py
roseingrave/_piece.py
roseingrave/_piece_data.py
roseingrave/_read_write.py
roseingrave/_shared.py
roseingrave/_sheets.py
roseingrave/_volunteer.py
roseingrave/compile_pieces.py
roseingrave/create_sheet.py
roseingrave/defaults/roseingrave.json
roseingrave/defaults/template_definitions.json
roseingrave/export_summary.py
roseingrave/fix_input.py
roseingrave/import_summary.py
roseingrave/piece_summary.py
roseingrave/reauth.py
roseingrave/volunteer_summary.py
roseingrave-1.1.0.dist-info/WHEEL
roseingrave-1.1.0.dist-info/entry_points.txt
roseingrave-1.1.0.dist-info/METADATA
roseingrave-1.1.0.dist-info/RECORD
