Metadata-Version: 2.1
Name: roseingrave
Version: 1.1.0
Summary: A massively scalable document source comparator, using Google Spreadsheets API + Python.
Home-page: https://github.com/scarlatti/roseingrave
License: LGPL-3.0-or-later
Keywords: digital humanities
Author: Joseph Lou
Author-email: jdlou@princeton.edu
Requires-Python: >=3.9,<4.0
Classifier: Development Status :: 4 - Beta
Classifier: License :: OSI Approved :: GNU Lesser General Public License v3 or later (LGPLv3+)
Classifier: Programming Language :: Python :: 3
Classifier: Programming Language :: Python :: 3.9
Classifier: Programming Language :: Python :: 3.10
Classifier: Programming Language :: Python :: 3.11
Classifier: Programming Language :: Python :: 3.9
Classifier: Topic :: Software Development :: Libraries :: Python Modules
Requires-Dist: cachetools (==5.2.0)
Requires-Dist: certifi (==2022.6.15)
Requires-Dist: charset-normalizer (==2.0.12)
Requires-Dist: click (==8.1.3)
Requires-Dist: google-auth (==2.9.0)
Requires-Dist: google-auth-oauthlib (==0.5.2)
Requires-Dist: gspread (==5.5.0)
Requires-Dist: idna (==3.3)
Requires-Dist: loguru (==0.6.0)
Requires-Dist: oauthlib (==3.2.0)
Requires-Dist: pyasn1 (==0.4.8)
Requires-Dist: pyasn1-modules (==0.2.8)
Requires-Dist: requests (==2.28.0)
Requires-Dist: requests-oauthlib (==1.3.1)
Requires-Dist: rsa (==4.8)
Requires-Dist: six (==1.16.0)
Requires-Dist: urllib3 (==1.26.9)
Project-URL: Repository, https://github.com/scarlatti/roseingrave
